dash_sign/DashSign.py
dash_sign/__init__.py
dash_sign/_imports_.py
dash_sign/dash_sign.min.js
dash_sign/dash_sign.min.js.map
dash_sign/metadata.json
dash_sign/package-info.json
dash_sign-0.0.2.dist-info/LICENSE
dash_sign-0.0.2.dist-info/METADATA
dash_sign-0.0.2.dist-info/WHEEL
dash_sign-0.0.2.dist-info/top_level.txt
dash_sign-0.0.2.dist-info/RECORD
