Metadata-Version: 2.1
Name: dash_sign
Version: 0.0.2
Summary: signature canvas for dash
Author: Daniel Patterson <d.p.patterson@outlook.com>
License: MIT
Classifier: Framework :: Dash
License-File: LICENSE
